pdrepr/__init__.py
pdrepr/_pdrepr.py
pdrepr-0.2.1.dist-info/LICENSE
pdrepr-0.2.1.dist-info/WHEEL
pdrepr-0.2.1.dist-info/METADATA
pdrepr-0.2.1.dist-info/RECORD
