Metadata-Version: 2.1
Name: pdrepr
Version: 0.2.1
Summary: eval-able string representation of pandas objects
Home-page: https://github.com/danhje/pdrepr
License: MIT
Keywords: pandas,dataframe,repr,string,eval
Author: Daniel Hjertholm
Author-email: daniel.hjertholm@icloud.com
Requires-Python: >=3.8,<4.0
Classifier: Development Status :: 4 - Beta
Classifier: Intended Audience :: Developers
Classifier: License :: OSI Approved :: MIT License
Classifier: Natural Language :: English
Classifier: Operating System :: OS Independent
Classifier: Programming Language :: Python :: 3
Classifier: Programming Language :: Python :: 3.10
Classifier: Programming Language :: Python :: 3.8
Classifier: Programming Language :: Python :: 3.9
Classifier: Topic :: Scientific/Engineering
Classifier: Topic :: Software Development :: Libraries
Classifier: Topic :: Software Development :: Libraries :: Python Modules
Classifier: Topic :: Software Development :: Testing
Requires-Dist: pandas
Project-URL: Repository, https://github.com/danhje/pdrepr
